my_library/__init__.py
my_library/core.py
alphabet_of_languages-0.1.2.dist-info/LICENSE
alphabet_of_languages-0.1.2.dist-info/METADATA
alphabet_of_languages-0.1.2.dist-info/WHEEL
alphabet_of_languages-0.1.2.dist-info/top_level.txt
alphabet_of_languages-0.1.2.dist-info/RECORD
